yina/__init__.py
yina/cli.py
yina/config.py
yina/linter.py
yina/validators.py
yina/config/yina.toml
yina-0.1.9.dist-info/METADATA
yina-0.1.9.dist-info/WHEEL
yina-0.1.9.dist-info/entry_points.txt
yina-0.1.9.dist-info/top_level.txt
yina-0.1.9.dist-info/RECORD
