Metadata-Version: 2.4
Name: yina
Version: 0.1.9
Summary: A Python linter focused on naming conventions with 5 strictness levels
Requires-Python: >=3.11
Requires-Dist: colorama>=0.4.6
Requires-Dist: pathspec>=0.12.1
Requires-Dist: tomli>=2.3.0
Requires-Dist: tomli-w>=1.2.0
